Metadata-Version: 1.0
Name: inscodegpt
Version: 1.4
Summary: Inscode GPT API python package
Home-page: UNKNOWN
Author: Yanhui
Author-email: yanhui@csdn.net
License: UNKNOWN
Platform: UNKNOWN
